{
	"tags": [
		{
			"position": [ 1319.1062, 945.1496, 51.7656 ],
			"angles": [ -0.00001, 0.00003, -2.60052 ],
			"segment": [ 0, 0 ]
		},
		{
			"position": [ 1319.07275, 945.20532, 51.7656 ],
			"angles": [ -0.0, 0.0, -2.60054 ],
			"segment": [ 0, 0 ]
		},
		{
			"position": [ 1534.95251, 847.29083, 43.4893 ],
			"angles": [ -0.0, -0.0, -1.74533 ],
			"segment": [ 0, 0 ]
		},
		{
			"position": [ 1604.9729, 896.14478, 49.45153 ],
			"angles": [ 0.056, 0.0, -0.98533 ],
			"segment": [ 0, 0 ]
		},
		{
			"position": [ 1647.00891, 856.08887, 55.23399 ],
			"angles": [ -0.0, 0.0, 2.05949 ],
			"segment": [ 0, 0 ]
		},
		{
			"position": [ 1710.35962, 548.30969, 56.77985 ],
			"angles": [ -0.004, 0.0, 1.93349 ],
			"segment": [ 0, 0 ]
		},
		{
			"position": [ 1548.79883, 1024.81458, 19.71668 ],
			"angles": [ -0.05401, 0.0, 2.77466 ],
			"segment": [ 0, 0 ]
		},
		{
			"position": [ 0.0, 0.0, 0.0 ],
			"angles": [ 0.0, 0.0, 0.0 ],
			"segment": [ 0, 0 ]
		},
		{
			"position": [ 0.0, 0.0, 0.0 ],
			"angles": [ 0.0, 0.0, 0.0 ],
			"segment": [ 0, 0 ]
		},
		{
			"position": [ 0.0, 0.0, 0.0 ],
			"angles": [ 0.0, 0.0, 0.0 ],
			"segment": [ 0, 0 ]
		},
		{
			"position": [ 0.0, 0.0, 0.0 ],
			"angles": [ 0.0, 0.0, 0.0 ],
			"segment": [ 0, 0 ]
		},
		{
			"position": [ 0.0, 0.0, 0.0 ],
			"angles": [ 0.0, 0.0, 0.0 ],
			"segment": [ 0, 0 ]
		}
	]
}